{"count": 2, "next": null, "previous": null, "results": [{"id": "10650ea2-29f0-4632-bde0-152418964e00", "url": "https://ll.thespacedevs.com/2.3.0/launches/10650ea2-29f0-4632-bde0-152418964e00/", "name": "Soyuz 2.1b | Kosmos 2570 (Lotos-S1 #8)", "response_mode": "normal", "slug": "soyuz-21b-kosmos-2570-lotos-s1-8", "launch_designator": "2023-165", "status": {"id": 3, "name": "Launch Successful", "abbrev": "Success", "description": "The launch vehicle successfully inserted its payload(s) into the target orbit(s)."}, "last_updated": "2024-03-05T18:01:41Z", "net": "2023-10-27T06:04:43Z", "net_precision": {"id": 0, "name": "Second", "abbrev": "SEC", "description": "The T-0 is accurate to the second."}, "window_end": "2023-10-27T08:00:00Z", "window_start": "2023-10-27T04:00:00Z", "image": {"id": 1333, "name": "[AUTO] Soyuz 2.1b | Kosmos 2570 (Lotos-S1 #8) - image", "image_url": "https://thespacedevs-prod.nyc3.digitaloceanspaces.com/media/images/soyuz25202.1b_image_20231029095145.jpg", "thumbnail_url": "https://thespacedevs-prod.nyc3.digitaloceanspaces.com/media/images/255bauto255d__image_thumbnail_20240305192431.jpeg", "credit": null, "license": {"id": 1, "name": "Unknown", "priority": 9, "link": null}, "single_use": true, "variants": []}, "infographic": null, "probability": null, "weather_concerns": null, "failreason": "", "hashtag": null, "launch_service_provider": {"response_mode": "list", "id": 193, "url": "https://ll.thespacedevs.com/2.3.0/agencies/193/", "name": "Russian Space Forces", "abbrev": "VKS", "type": {"id": 1, "name": "Government"}}, "rocket": {"id": 8055, "configuration": {"response_mode": "list", "id": 15, "url": "https://ll.thespacedevs.com/2.3.0/launcher_configurations/15/", "name": "Soyuz 2.1b", "families": [{"response_mode": "list", "id": 147, "name": "Soyuz"}, {"response_mode": "list", "id": 190, "name": "Soyuz 2"}], "full_name": "Soyuz 2.1b", "variant": ""}}, "mission": {"id": 6603, "name": "Kosmos 2570 (Lotos-S1 #8)", "type": "Government/Top Secret", "description": "Note: Payload identity uncertain. Multiple other military payloads that are not identified may be on board.\r\n\r\nLotos-S1 spacecraft is a part of the Liana constellation, designed for orbital electronic intelligence.", "image": null, "orbit": {"id": 8, "name": "Low Earth Orbit", "abbrev": "LEO", "celestial_body": {"response_mode": "list", "id": 1, "name": "Earth"}}, "agencies": [], "info_urls": [], "vid_urls": []}, "pad": {"id": 36, "url": "https://ll.thespacedevs.com/2.3.0/pads/36/", "active": true, "agencies": [{"response_mode": "normal", "id": 163, "url": "https://ll.thespacedevs.com/2.3.0/agencies/163/", "name": "Russian Aerospace Defence Forces", "abbrev": "VKO", "type": {"id": 1, "name": "Government"}, "featured": false, "country": [{"id": 5, "name": "Russia", "alpha_2_code": "RU", "alpha_3_code": "RUS", "nationality_name": "Russian", "nationality_name_composed": "Russo"}], "description": null, "administrator": null, "founding_year": null, "launchers": "", "spacecraft": "", "parent": "Russian Federal Space Agency (ROSCOSMOS)", "image": null, "logo": null, "social_logo": null}], "name": "43/3 (43L)", "image": {"id": 1461, "name": "Soyuz 2.1b/Fregat-M liftoff from pad 43/3 (Glonass-K2 No. 13, Kosmos 2569)", "image_url": "https://thespacedevs-prod.nyc3.digitaloceanspaces.com/media/images/soyuz25202.1b_image_20230807181912.jpg", "thumbnail_url": "https://thespacedevs-prod.nyc3.digitaloceanspaces.com/media/images/255bauto255d__image_thumbnail_20240305192834.jpeg", "credit": "Mil.ru", "license": {"id": 30, "name": "CC BY 4.0", "priority": 4, "link": "https://creativecommons.org/licenses/by/4.0/"}, "single_use": false, "variants": []}, "description": "", "info_url": null, "wiki_url": null, "map_url": "https://www.google.com/maps?q=62.9273,40.45", "latitude": 62.9273, "longitude": 40.45, "country": {"id": 5, "name": "Russia", "alpha_2_code": "RU", "alpha_3_code": "RUS", "nationality_name": "Russian", "nationality_name_composed": "Russo"}, "map_image": "https://thespacedevs-prod.nyc3.digitaloceanspaces.com/media/map_images/pad_36_20200803143534.jpg", "total_launch_count": 232, "orbital_launch_attempt_count": 232, "fastest_turnaround": "P2DT17H44M", "location": {"response_mode": "normal", "id": 6, "url": "https://ll.thespacedevs.com/2.3.0/locations/6/", "name": "Plesetsk Cosmodrome, Russian Federation", "celestial_body": {"response_mode": "normal", "id": 1, "name": "Earth", "type": {"id": 1, "name": "Planet"}, "diameter": 12742000.0, "mass": 5.972168e+24, "gravity": 9.80655, "length_of_day": "1 00:00:00", "atmosphere": true, "image": {"id": 2040, "name": "Earth (Apollo 17)", "image_url": "https://thespacedevs-prod.nyc3.digitaloceanspaces.com/media/images/earth_2528apol_image_20240402194304.jpeg", "thumbnail_url": "https://thespacedevs-prod.nyc3.digitaloceanspaces.com/media/images/earth_2528apol_image_thumbnail_20240402194305.jpeg", "credit": "NASA", "license": {"id": 4, "name": "NASA Image and Media Guidelines", "priority": 0, "link": "https://www.nasa.gov/nasa-brand-center/images-and-media/"}, "single_use": true, "variants": []}, "description": "Earth is the third planet from the Sun and the only astronomical object known to harbor life.", "wiki_url": "https://en.wikipedia.org/wiki/Earth", "total_attempted_launches": 7501, "successful_launches": 6945, "failed_launches": 556, "total_attempted_landings": 1305, "successful_landings": 1258, "failed_landings": 47}, "active": true, "country": {"id": 5, "name": "Russia", "alpha_2_code": "RU", "alpha_3_code": "RUS", "nationality_name": "Russian", "nationality_name_composed": "Russo"}, "description": "Plesetsk Cosmodrome is a Russian spaceport located in Mirny, Arkhangelsk Oblast, about 800 km north of Moscow and approximately 200 km south of Arkhangelsk. Originally developed as an ICBM site for the R-7 missile, it also served for numerous satellite launches using the R-7 and other rockets. Its high latitude makes it useful only for certain types of launches, especially the Molniya orbits, so for much of the site's history it functioned as a secondary location, with most orbital launches taking place from Baikonur, in the Kazakh SSR. With the end of the Soviet Union, Baikonur became a foreign territory, and Kazakhstan charged $115 million usage fees annually. Consequently, Plesetsk has seen considerably more activity since the 2000s.", "image": {"id": 1461, "name": "Soyuz 2.1b/Fregat-M liftoff from pad 43/3 (Glonass-K2 No. 13, Kosmos 2569)", "image_url": "https://thespacedevs-prod.nyc3.digitaloceanspaces.com/media/images/soyuz25202.1b_image_20230807181912.jpg", "thumbnail_url": "https://thespacedevs-prod.nyc3.digitaloceanspaces.com/media/images/255bauto255d__image_thumbnail_20240305192834.jpeg", "credit": "Mil.ru", "license": {"id": 30, "name": "CC BY 4.0", "priority": 4, "link": "https://creativecommons.org/licenses/by/4.0/"}, "single_use": false, "variants": []}, "map_image": "https://thespacedevs-prod.nyc3.digitaloceanspaces.com/media/map_images/location_6_20200803142434.jpg", "longitude": 40.577778, "latitude": 62.925556, "timezone_name": "Europe/Moscow", "total_launch_count": 1685, "total_landing_count": 0}}, "webcast_live": false, "program": [], "orbital_launch_attempt_count": 6542, "location_launch_attempt_count": 1663, "pad_launch_attempt_count": 229, "agency_launch_attempt_count": 136, "orbital_launch_attempt_count_year": 174, "location_launch_attempt_count_year": 4, "pad_launch_attempt_count_year": 3, "agency_launch_attempt_count_year": 4}, {"id": "9bfd7559-da1a-4286-baf8-e2342d55ef52", "url": "https://ll.thespacedevs.com/2.3.0/launches/9bfd7559-da1a-4286-baf8-e2342d55ef52/", "name": "Falcon 9 Block 5 | Starlink Group 7-6", "response_mode": "normal", "slug": "falcon-9-block-5-starlink-group-7-6", "launch_designator": "2023-166", "status": {"id": 3, "name": "Launch Successful", "abbrev": "Success", "description": "The launch vehicle successfully inserted its payload(s) into the target orbit(s)."}, "last_updated": "2025-09-25T13:46:01Z", "net": "2023-10-29T09:00:00Z", "net_precision": {"id": 0, "name": "Second", "abbrev": "SEC", "description": "The T-0 is accurate to the second."}, "window_end": "2023-10-29T10:08:40Z", "window_start": "2023-10-29T09:00:00Z", "image": {"id": 1296, "name": "Starlink night fairing", "image_url": "https://thespacedevs-prod.nyc3.digitaloceanspaces.com/media/images/falcon2520925_image_20221009234147.png", "thumbnail_url": "https://thespacedevs-prod.nyc3.digitaloceanspaces.com/media/images/255bauto255d__image_thumbnail_20240305192320.png", "credit": "SpaceX", "license": {"id": 5, "name": "CC BY-NC 2.0", "priority": 1, "link": "https://creativecommons.org/licenses/by-nc/2.0/"}, "single_use": false, "variants": []}, "infographic": null, "probability": null, "weather_concerns": null, "failreason": "", "hashtag": null, "launch_service_provider": {"response_mode": "list", "id": 121, "url": "https://ll.thespacedevs.com/2.3.0/agencies/121/", "name": "SpaceX", "abbrev": "SpX", "type": {"id": 3, "name": "Commercial"}}, "rocket": {"id": 7953, "configuration": {"response_mode": "list", "id": 164, "url": "https://ll.thespacedevs.com/2.3.0/launcher_configurations/164/", "name": "Falcon 9", "families": [{"response_mode": "list", "id": 1, "name": "Falcon"}, {"response_mode": "list", "id": 176, "name": "Falcon 9"}], "full_name": "Falcon 9 Block 5", "variant": "Block 5"}}, "mission": {"id": 6469, "name": "Starlink Group 7-6", "type": "Communications", "description": "A batch of 22 satellites for the Starlink mega-constellation - SpaceX's project for space-based Internet communication system.", "image": null, "orbit": {"id": 8, "name": "Low Earth Orbit", "abbrev": "LEO", "celestial_body": {"response_mode": "list", "id": 1, "name": "Earth"}}, "agencies": [{"response_mode": "normal", "id": 121, "url": "https://ll.thespacedevs.com/2.3.0/agencies/121/", "name": "SpaceX", "abbrev": "SpX", "type": {"id": 3, "name": "Commercial"}, "featured": true, "country": [{"id": 2, "name": "United States of America", "alpha_2_code": "US", "alpha_3_code": "USA", "nationality_name": "American", "nationality_name_composed": "Americano"}], "description": "Space Exploration Technologies Corp., known as SpaceX, is an American aerospace manufacturer and space transport services company headquartered in Hawthorne, California. It was founded in 2002 by entrepreneur Elon Musk with the goal of reducing space transportation costs and enabling the colonization of Mars. SpaceX operates from many pads, on the East Coast of the US they operate from SLC-40 at Cape Canaveral Space Force Station and historic LC-39A at Kennedy Space Center. They also operate from SLC-4E at Vandenberg Space Force Base, California, usually for polar launches. Another launch site is being developed at Boca Chica, Texas.", "administrator": "CEO: Elon Musk", "founding_year": 2002, "launchers": "Falcon | Starship", "spacecraft": "Dragon", "parent": null, "image": {"id": 1736, "name": "Falcon 9 liftoff from LC-39A", "image_url": "https://thespacedevs-prod.nyc3.digitaloceanspaces.com/media/images/falcon_9_image_20230807133459.jpeg", "thumbnail_url": "https://thespacedevs-prod.nyc3.digitaloceanspaces.com/media/images/255bauto255d__image_thumbnail_20240305193628.jpeg", "credit": "SpaceX", "license": {"id": 5, "name": "CC BY-NC 2.0", "priority": 1, "link": "https://creativecommons.org/licenses/by-nc/2.0/"}, "single_use": false, "variants": []}, "logo": {"id": 186, "name": "SpaceX logo", "image_url": "https://thespacedevs-prod.nyc3.digitaloceanspaces.com/media/images/spacex_logo_20220826094919.png", "thumbnail_url": "https://thespacedevs-prod.nyc3.digitaloceanspaces.com/media/images/255bauto255d__image_thumbnail_20240305185138.png", "credit": "SpaceX", "license": {"id": 5, "name": "CC BY-NC 2.0", "priority": 1, "link": "https://creativecommons.org/licenses/by-nc/2.0/"}, "single_use": true, "variants": []}, "social_logo": {"id": 94, "name": "SpaceX social logo", "image_url": "https://thespacedevs-prod.nyc3.digitaloceanspaces.com/media/images/spacex_social_l_image_20260407054626.jpg", "thumbnail_url": "https://thespacedevs-prod.nyc3.digitaloceanspaces.com/media/images/spacex_social_l_image_thumbnail_20260407054626.jpeg", "credit": "SpaceX", "license": {"id": 5, "name": "CC BY-NC 2.0", "priority": 1, "link": "https://creativecommons.org/licenses/by-nc/2.0/"}, "single_use": true, "variants": []}, "total_launch_count": 674, "consecutive_successful_launches": 159, "successful_launches": 659, "failed_launches": 15, "pending_launches": 120, "consecutive_successful_landings": 159, "successful_landings": 620, "failed_landings": 27, "attempted_landings": 646, "successful_landings_spacecraft": 59, "failed_landings_spacecraft": 3, "attempted_landings_spacecraft": 63, "successful_landings_payload": 0, "failed_landings_payload": 0, "attempted_landings_payload": 0, "info_url": "https://www.spacex.com/", "wiki_url": "https://en.wikipedia.org/wiki/SpaceX", "social_media_links": [{"id": 427, "social_media": {"id": 3, "name": "Homepage", "url": null, "logo": null}, "url": "https://www.spacex.com/"}, {"id": 428, "social_media": {"id": 1, "name": "X", "url": "https://x.com", "logo": {"id": 2320, "name": "X logo", "image_url": "https://thespacedevs-prod.nyc3.digitaloceanspaces.com/media/images/x_logo_image_20250211191027.jpg", "thumbnail_url": "https://thespacedevs-prod.nyc3.digitaloceanspaces.com/media/images/x_logo_image_thumbnail_20250211191027.jpeg", "credit": "X", "license": {"id": 1, "name": "Unknown", "priority": 9, "link": null}, "single_use": true, "variants": []}}, "url": "https://x.com/spacex/"}, {"id": 429, "social_media": {"id": 6, "name": "Youtube", "url": "https://www.youtube.com/", "logo": {"id": 2356, "name": "YouTube logo", "image_url": "https://thespacedevs-prod.nyc3.digitaloceanspaces.com/media/images/youtube_logo_image_20250321073112.png", "thumbnail_url": "https://thespacedevs-prod.nyc3.digitaloceanspaces.com/media/images/youtube_logo_image_thumbnail_20250321073112.png", "credit": "YouTube", "license": {"id": 1, "name": "Unknown", "priority": 9, "link": null}, "single_use": true, "variants": []}}, "url": "https://www.youtube.com/@spacex"}, {"id": 430, "social_media": {"id": 4, "name": "LinkedIn", "url": "https://www.linkedin.com/", "logo": {"id": 2321, "name": "LinkedIn logo", "image_url": "https://thespacedevs-prod.nyc3.digitaloceanspaces.com/media/images/linkedin_logo_image_20250211191111.png", "thumbnail_url": "https://thespacedevs-prod.nyc3.digitaloceanspaces.com/media/images/linkedin_logo_image_thumbnail_20250211191112.png", "credit": "LinkedIn", "license": {"id": 1, "name": "Unknown", "priority": 9, "link": null}, "single_use": true, "variants": []}}, "url": "https://www.linkedin.com/company/spacex/"}]}], "info_urls": [], "vid_urls": []}, "pad": {"id": 16, "url": "https://ll.thespacedevs.com/2.3.0/pads/16/", "active": true, "agencies": [], "name": "Space Launch Complex 4E", "image": {"id": 1342, "name": "Falcon 9 Block 5 | SARah 2 & 3 from SLC-4E", "image_url": "https://thespacedevs-prod.nyc3.digitaloceanspaces.com/media/images/falcon2520925_image_20231223073520.jpeg", "thumbnail_url": "https://thespacedevs-prod.nyc3.digitaloceanspaces.com/media/images/255bauto255d__image_thumbnail_20240305192449.jpeg", "credit": "SpaceX", "license": {"id": 5, "name": "CC BY-NC 2.0", "priority": 1, "link": "https://creativecommons.org/licenses/by-nc/2.0/"}, "single_use": false, "variants": []}, "description": "Space Launch Complex 4 East (SLC-4E) is a launch site at Vandenberg Space Force Base, California, U.S.\r\n\r\nThe pad was previously used by Atlas and Titan rockets between 1963 and 2005. The pad was built for use by Atlas-Agena rockets, but was later rebuilt to handle Titan rockets.", "info_url": null, "wiki_url": "https://en.wikipedia.org/wiki/Vandenberg_Space_Launch_Complex_4#SLC-4E", "map_url": "https://www.google.com/maps?q=34.632,-120.611", "latitude": 34.632, "longitude": -120.611, "country": {"id": 2, "name": "United States of America", "alpha_2_code": "US", "alpha_3_code": "USA", "nationality_name": "American", "nationality_name_composed": "Americano"}, "map_image": "https://thespacedevs-prod.nyc3.digitaloceanspaces.com/media/map_images/pad_16_20200803143532.jpg", "total_launch_count": 266, "orbital_launch_attempt_count": 266, "fastest_turnaround": "P2DT10H22M59S", "location": {"response_mode": "normal", "id": 11, "url": "https://ll.thespacedevs.com/2.3.0/locations/11/", "name": "Vandenberg SFB, CA, USA", "celestial_body": {"response_mode": "normal", "id": 1, "name": "Earth", "type": {"id": 1, "name": "Planet"}, "diameter": 12742000.0, "mass": 5.972168e+24, "gravity": 9.80655, "length_of_day": "1 00:00:00", "atmosphere": true, "image": {"id": 2040, "name": "Earth (Apollo 17)", "image_url": "https://thespacedevs-prod.nyc3.digitaloceanspaces.com/media/images/earth_2528apol_image_20240402194304.jpeg", "thumbnail_url": "https://thespacedevs-prod.nyc3.digitaloceanspaces.com/media/images/earth_2528apol_image_thumbnail_20240402194305.jpeg", "credit": "NASA", "license": {"id": 4, "name": "NASA Image and Media Guidelines", "priority": 0, "link": "https://www.nasa.gov/nasa-brand-center/images-and-media/"}, "single_use": true, "variants": []}, "description": "Earth is the third planet from the Sun and the only astronomical object known to harbor life.", "wiki_url": "https://en.wikipedia.org/wiki/Earth", "total_attempted_launches": 7501, "successful_launches": 6945, "failed_launches": 556, "total_attempted_landings": 1305, "successful_landings": 1258, "failed_landings": 47}, "active": true, "country": {"id": 2, "name": "United States of America", "alpha_2_code": "US", "alpha_3_code": "USA", "nationality_name": "American", "nationality_name_composed": "Americano"}, "description": "Vandenberg Space Force Base is a United States Space Force Base in Santa Barbara County, California. Established in 1941, Vandenberg Space Force Base is a space launch base, launching spacecraft from the Western Range, and also performs missile testing. The United States Space Force's Space Launch Delta 30 serves as the host delta for the base, equivalent to an Air Force air base wing. In addition to its military space launch mission, Vandenberg Space Force Base also hosts space launches for civil and commercial space entities, such as NASA and SpaceX.", "image": {"id": 2226, "name": "Vandenberg SFB imaged by Sentinel-2", "image_url": "https://thespacedevs-prod.nyc3.digitaloceanspaces.com/media/images/vandenberg_sfb__image_20240920082910.jpeg", "thumbnail_url": "https://thespacedevs-prod.nyc3.digitaloceanspaces.com/media/images/vandenberg_sfb__image_thumbnail_20240920082910.jpeg", "credit": "Contains modified Copernicus Sentinel data 2020", "license": {"id": 33, "name": "Copernicus Image Use Policy", "priority": 0, "link": "https://eur-lex.europa.eu/legal-content/EN/TXT/?uri=CELEX:32013R1159"}, "single_use": true, "variants": []}, "map_image": "https://thespacedevs-prod.nyc3.digitaloceanspaces.com/media/map_images/location_11_20200803142416.jpg", "longitude": -120.52023, "latitude": 34.75133, "timezone_name": "America/Los_Angeles", "total_launch_count": 882, "total_landing_count": 34}}, "webcast_live": false, "program": [{"response_mode": "normal", "id": 25, "url": "https://ll.thespacedevs.com/2.3.0/programs/25/", "name": "Starlink", "image": {"id": 1890, "name": "Starlink stack in space before deployment", "image_url": "https://thespacedevs-prod.nyc3.digitaloceanspaces.com/media/images/starlink_program_20231228154508.jpeg", "thumbnail_url": "https://thespacedevs-prod.nyc3.digitaloceanspaces.com/media/images/255bauto255d__image_thumbnail_20240305194044.jpeg", "credit": "SpaceX", "license": {"id": 5, "name": "CC BY-NC 2.0", "priority": 1, "link": "https://creativecommons.org/licenses/by-nc/2.0/"}, "single_use": true, "variants": []}, "info_url": "https://starlink.com", "wiki_url": "https://en.wikipedia.org/wiki/Starlink", "description": "Starlink is a satellite internet constellation operated by American aerospace company SpaceX", "agencies": [{"response_mode": "list", "id": 121, "url": "https://ll.thespacedevs.com/2.3.0/agencies/121/", "name": "SpaceX", "abbrev": "SpX", "type": {"id": 3, "name": "Commercial"}}], "start_date": "2018-02-22T14:17:00Z", "end_date": null, "mission_patches": [{"id": 7, "name": "Space X Starlink Mission Patch", "priority": 10, "image_url": "https://thespacedevs-prod.nyc3.digitaloceanspaces.com/media/mission_patch_images/space2520x252_mission_patch_20221011205756.png", "agency": {"response_mode": "list", "id": 121, "url": "https://ll.thespacedevs.com/2.3.0/agencies/121/", "name": "SpaceX", "abbrev": "SpX", "type": {"id": 3, "name": "Commercial"}}, "response_mode": "normal"}], "type": {"id": 3, "name": "Communication Constellation"}}], "orbital_launch_attempt_count": 6543, "location_launch_attempt_count": 733, "pad_launch_attempt_count": 123, "agency_launch_attempt_count": 291, "orbital_launch_attempt_count_year": 175, "location_launch_attempt_count_year": 24, "pad_launch_attempt_count_year": 23, "agency_launch_attempt_count_year": 78}]}